{
  "buildCommand" : {
    "command" : "build",
    "skipDependencies" : false,
    "style" : "buildAndRun"
  },
  "configuredTargets" : [
    {
      "guid" : "a7307de17fe8c275fe92cd97c47ccec431d89a7cc72055bdded1838419779aa5"
    }
  ],
  "containerPath" : "/Users/admin/Documents/SQliteSIL/SQliteSIL.xcodeproj",
  "continueBuildingAfterErrors" : false,
  "dependencyScope" : "workspace",
  "enableIndexBuildArena" : false,
  "hideShellScriptEnvironment" : false,
  "parameters" : {
    "action" : "build",
    "overrides" : {
      "commandLine" : {
        "table" : {
          "CODE_SIGN_IDENTITY" : "\"\"",
          "CODE_SIGNING_ALLOWED" : "NO",
          "CODE_SIGNING_REQUIRED" : "NO",
          "OTHER_SWIFT_FLAGS" : "-Xfrontend -gsil -Xllvm -sil-print-debuginfo -Xllvm -sil-print-before=SerializeSILPass",
          "SWIFT_COMPILATION_MODE" : "wholemodule"
        }
      },
      "synthesized" : {
        "table" : {
          "ACTION" : "build",
          "ENABLE_PREVIEWS" : "NO",
          "ENABLE_XOJIT_PREVIEWS" : "NO"
        }
      }
    }
  },
  "showNonLoggedProgress" : true,
  "useDryRun" : false,
  "useImplicitDependencies" : false,
  "useLegacyBuildLocations" : false,
  "useParallelTargets" : true
}